hd2api/__init__.py
hd2api/api_config.py
hd2api/load_json.py
hd2api/builders/__init__.py
hd2api/builders/assignment_builder.py
hd2api/builders/campaign_builder.py
hd2api/builders/effect_builder.py
hd2api/builders/planet_builder.py
hd2api/builders/region_builder.py
hd2api/builders/sector_state_builder.py
hd2api/builders/statistics_builder.py
hd2api/builders/war_builder.py
hd2api/constants/__init__.py
hd2api/constants/constants.py
hd2api/loggingsubmodule/__init__.py
hd2api/loggingsubmodule/logging.py
hd2api/models/Assignment2.py
hd2api/models/Biome.py
hd2api/models/Campaign2.py
hd2api/models/Dispatch.py
hd2api/models/DiveharderAll.py
hd2api/models/Effects.py
hd2api/models/Event.py
hd2api/models/GalaxyStatic.py
hd2api/models/Hazard.py
hd2api/models/Planet.py
hd2api/models/Position.py
hd2api/models/Region.py
hd2api/models/Reward2.py
hd2api/models/SectorState.py
hd2api/models/SpaceStation2.py
hd2api/models/Statistics.py
hd2api/models/SteamNews.py
hd2api/models/Task2.py
hd2api/models/War.py
hd2api/models/__init__.py
hd2api/models/ABC/__init__.py
hd2api/models/ABC/model.py
hd2api/models/Base/Assignment.py
hd2api/models/Base/Campaign.py
hd2api/models/Base/Cost.py
hd2api/models/Base/Effects.py
hd2api/models/Base/GalaxyStats.py
hd2api/models/Base/GlobalEvent.py
hd2api/models/Base/GlobalResource.py
hd2api/models/Base/HomeWorld.py
hd2api/models/Base/JointOperation.py
hd2api/models/Base/NewsFeedItem.py
hd2api/models/Base/PlanetAttack.py
hd2api/models/Base/PlanetCoordinates.py
hd2api/models/Base/PlanetEvent.py
hd2api/models/Base/PlanetInfo.py
hd2api/models/Base/PlanetRegion.py
hd2api/models/Base/PlanetRegionInfo.py
hd2api/models/Base/PlanetStats.py
hd2api/models/Base/PlanetStatus.py
hd2api/models/Base/Reward.py
hd2api/models/Base/Setting.py
hd2api/models/Base/SpaceStation.py
hd2api/models/Base/SteamNewsRaw.py
hd2api/models/Base/TacticalActions.py
hd2api/models/Base/Task.py
hd2api/models/Base/WarId.py
hd2api/models/Base/WarInfo.py
hd2api/models/Base/WarStatus.py
hd2api_py-0.0.1.20.20.dist-info/licenses/LICENSE
hd2api_py-0.0.1.20.20.dist-info/METADATA
hd2api_py-0.0.1.20.20.dist-info/WHEEL
hd2api_py-0.0.1.20.20.dist-info/top_level.txt
hd2api_py-0.0.1.20.20.dist-info/RECORD
