Metadata-Version: 2.4
Name: hd2api.py
Version: 0.0.1.20.20
Summary: An API wrapper for the Helldivers 2 Community and official APIs
Author-email: Crosswave Omega <taucetivse@gmail.com>
Project-URL: Documentation, https://hd2apipy.readthedocs.io/en/latest/
Project-URL: Source, https://github.com/CrosswaveOmega/hd2api.py
Project-URL: Tracker, https://github.com/CrosswaveOmega/hd2api.py/issues
Keywords: helldivers2,api
Classifier: Development Status :: 3 - Alpha
Classifier: Intended Audience :: Developers
Classifier: License :: OSI Approved :: MIT License
Classifier: Programming Language :: Python :: 3 :: Only
Classifier: Programming Language :: Python :: 3.8
Classifier: Programming Language :: Python :: 3.9
Classifier: Programming Language :: Python :: 3.10
Classifier: Programming Language :: Python :: 3.11
Requires-Python: >=3.8.1
License-File: LICENSE
Requires-Dist: pydantic>=2.9.2
Requires-Dist: httpx>=0.27.2
Provides-Extra: spark
Requires-Dist: pyspark>=4.0.0; extra == "spark"
Provides-Extra: test
Requires-Dist: bandit[toml]==1.8.6; extra == "test"
Requires-Dist: black==25.1.0; extra == "test"
Requires-Dist: check-manifest==0.50; extra == "test"
Requires-Dist: flake8-bugbear==24.12.12; extra == "test"
Requires-Dist: flake8-docstrings; extra == "test"
Requires-Dist: flake8-formatter_junit_xml; extra == "test"
Requires-Dist: flake8; extra == "test"
Requires-Dist: flake8-pyproject; extra == "test"
Requires-Dist: pre-commit==4.3.0; extra == "test"
Requires-Dist: pylint==3.3.8; extra == "test"
Requires-Dist: pylint_junit; extra == "test"
Requires-Dist: pytest-cov==6.2.1; extra == "test"
Requires-Dist: pytest-mock<3.14.0; extra == "test"
Requires-Dist: pytest-runner; extra == "test"
Requires-Dist: pytest==8.4.1; extra == "test"
Requires-Dist: pytest-github-actions-annotate-failures; extra == "test"
Requires-Dist: shellcheck-py==0.11.0.1; extra == "test"
Requires-Dist: pytest-asyncio==1.1.0; extra == "test"
Provides-Extra: docs
Requires-Dist: sphinx>=8.2.3; extra == "docs"
Requires-Dist: autodoc_pydantic==2.2.0; extra == "docs"
Dynamic: license-file
